{
  "indexVersion": 1.1,
  "dateGenerated": "2025-12-08T10:41:55Z",
  "lastTweaked": "2025-12-11T11:30:00Z",
  "name": "Adult Media Hub",
  "description": "Dedicated repository for content containing adult media (XXX, Hentai, JAV, etc.). Providers listed here have explicit adult content.",
  "author": "Kiyomi Porn Curators",
  "iconUrl": "https://kiyomi-project.pages.dev/kiyomi-extensions/icons/adult_icon.jpg",
  "headerImageUrl": "https://kiyomi-project.pages.dev/kiyomi-extensions/images/erotic_bg.webp",
  "providers": [
    {
      "id": "thepiratebay-js",
      "name": "The Pirate Bay",
      "author": "Kiyomi Community",
      "configUrl": "https://kiyomi-project.pages.dev/kiyomi-extensions/providers_torrent_js/thepiratebay.js",
      "iconUrl": "https://torrindex.net/images/tpb.jpg",
      "description": "General purpose torrent indexer; includes an **Adult (XXX)** category for diverse content.",
      "isAdult": true,
      "isSecure": false,
      "cautionReason": "Search results are often unverified and may contain malicious files.",
      "isPrivate": false,
      "isApiKeyRequired": false,
      "version": 1,
      "backendType": "api"
    },
    {
      "id": "sukebei_nyaa-js",
      "name": "Sukebei Nyaa",
      "author": "Kiyomi Community",
      "configUrl": "https://kiyomi-project.pages.dev/kiyomi-extensions/providers_torrent_js/sukebei_nyaa.js",
      "iconUrl": "https://sukebei.nyaa.si/static/favicon.png",
      "description": "Dedicated adults-only sister site of Nyaa, specializing in 18+ Japanese/Asian media like Hentai and Doujinshi.",
      "isAdult": true,
      "isSecure": true,
      "cautionReason": "",
      "isPrivate": false,
      "isApiKeyRequired": false,
      "version": 1,
      "backendType": "rss"
    },
    {
      "id": "tokyotosho-js",
      "name": "TokyoTosho",
      "author": "Kiyomi Community",
      "configUrl": "https://kiyomi-project.pages.dev/kiyomi-extensions/providers_torrent_js/tokyotosho.js",
      "iconUrl": "https://www.tokyotosho.info/favicon.ico",
      "description": "General Eastern media index which includes **Hentai and JAV** categories.",
      "isAdult": true,
      "isSecure": true,
      "cautionReason": "Non-video content (e.g., games, software, archives) may contain malware.",
      "isPrivate": false,
      "isApiKeyRequired": false,
      "version": 1,
      "backendType": "rss"
    },
    {
      "id": "knaben-js",
      "name": "Knaben",
      "author": "Kiyomi Community",
      "configUrl": "https://kiyomi-project.pages.dev/kiyomi-extensions/providers_torrent_js/knaben.js",
      "iconUrl": "https://knaben.org/favicon.ico",
      "description": "Modern API providing structured results, including content that may fall under the adult category.",
      "isAdult": true,
      "isSecure": true,
      "cautionReason": "",
      "isPrivate": true,
      "isApiKeyRequired": true,
      "version": 1,
      "backendType": "api"
    },
    {
      "id": "btdig-js",
      "name": "BTDigg",
      "author": "Kiyomi Community",
      "configUrl": "https://kiyomi-project.pages.dev/kiyomi-extensions/providers_torrent_js/btdig.js",
      "iconUrl": "https://www.btdig.com/favicon.ico",
      "description": "Global DHT search engine, highly effective for locating *older, rare, or large archives* of adult content.",
      "isAdult": true,
      "isSecure": true,
      "cautionReason": "Search results are often unverified and may contain malicious files.",
      "isPrivate": false,
      "isApiKeyRequired": false,
      "version": 1.0,
      "backendType": "scrape"
    },
    {
      "id": "cloudtorrents-js",
      "name": "CloudTorrents",
      "author": "Kiyomi Community",
      "configUrl": "https://kiyomi-project.pages.dev/kiyomi-extensions/providers_torrent_js/cloudtorrents.js",
      "iconUrl": "https://cloudtorrents.com/assets/apple-touch-icon.png",
      "description": "Modern API-based indexer, useful as a structured search backup for diverse adult releases.",
      "isAdult": true,
      "isSecure": true,
      "cautionReason": "",
      "isPrivate": false,
      "isApiKeyRequired": false,
      "version": 1.0,
      "backendType": "api"
    },
    {
      "id": "filemood-js",
      "name": "FileMood",
      "author": "Kiyomi Community",
      "configUrl": "https://kiyomi-project.pages.dev/kiyomi-extensions/providers_torrent_js/filemood.js",
      "iconUrl": "https://filemood.com/favicon.ico",
      "description": "General indexer specializing in file search. Useful for niche or less-indexed adult archives.",
      "isAdult": true,
      "isSecure": false,
      "cautionReason": "Scraping results can be unstable.",
      "isPrivate": false,
      "isApiKeyRequired": false,
      "version": 1.0,
      "backendType": "scrape"
    },
    {
      "id": "torrentdownload-js",
      "name": "TorrentDownload",
      "author": "Kiyomi Community",
      "configUrl": "https://kiyomi-project.pages.dev/kiyomi-extensions/providers_torrent_js/torrentdownload.js",
      "iconUrl": "https://www.torrentdownload.info/favicon.ico",
      "description": "Public indexer with traditional scraping support; good for widely distributed XXX releases.",
      "isAdult": true,
      "isSecure": true,
      "cautionReason": "Scraping results can be unstable.",
      "isPrivate": false,
      "isApiKeyRequired": false,
      "version": 1.0,
      "backendType": "api"
    },
    {
      "id": "limetorrents-js",
      "name": "LimeTorrents",
      "author": "Kiyomi Community",
      "configUrl": "https://kiyomi-project.pages.dev/kiyomi-extensions/providers_torrent_js/limetorrents.js",
      "iconUrl": "https://www.limetorrents.fun/favicon.ico",
      "description": "General Torrents Download indexer; includes an extensive range of adult content categories.",
      "isAdult": true,
      "isSecure": false,
      "cautionReason": "Unverified public indexer. Contains potentially harmful/mislabelled torrents.",
      "isPrivate": false,
      "isApiKeyRequired": false,
      "version": 1.0,
      "backendType": "scrape"
    },
    {
      "id": "snowfl-js",
      "name": "Snowfl",
      "author": "Kiyomi Community",
      "configUrl": "https://kiyomi-project.pages.dev/kiyomi-extensions/providers_torrent_js/snowfl.js",
      "iconUrl": "https://snowfl.com/favicon.ico",
      "description": "General meta-search engine providing results from multiple sources; excellent for cross-checking availability.",
      "isAdult": true,
      "isSecure": true,
      "cautionReason": "External meta-search results can be unverified.",
      "isPrivate": false,
      "isApiKeyRequired": false,
      "version": 1.0,
      "backendType": "api"
    }
  ]
}